AUTHORS
LICENSE
MANIFEST.in
README.rst
setup.py
django_mailgun/__init__.py
django_mailgun_provider.egg-info/PKG-INFO
django_mailgun_provider.egg-info/SOURCES.txt
django_mailgun_provider.egg-info/dependency_links.txt
django_mailgun_provider.egg-info/requires.txt
django_mailgun_provider.egg-info/top_level.txt