Metadata-Version: 1.1
Name: django-mailgun-provider
Version: 0.2.3
Summary: A Django email backend for Mailgun
Home-page: http://github.com/bradwhittington/django-mailgun/
Author: Bradley Whittington
Author-email: radbrad182@gmail.com
License: MIT
Platform: any
Classifier: Development Status :: 4 - Beta
Classifier: Intended Audience :: Developers
Classifier: License :: OSI Approved :: MIT License
Classifier: Operating System :: OS Independent
Classifier: Programming Language :: Python
Classifier: Topic :: Software Development :: Libraries :: Python Modules
Classifier: Framework :: Django
